django_comments_ink/__init__.py
django_comments_ink/admin.py
django_comments_ink/apps.py
django_comments_ink/caching.py
django_comments_ink/forms.py
django_comments_ink/models.py
django_comments_ink/moderation.py
django_comments_ink/paginator.py
django_comments_ink/partial.py
django_comments_ink/signals.py
django_comments_ink/signed.py
django_comments_ink/urls.py
django_comments_ink/utils.py
django_comments_ink/api/__init__.py
django_comments_ink/api/frontend.py
django_comments_ink/api/serializers.py
django_comments_ink/api/urls.py
django_comments_ink/api/views.py
django_comments_ink/conf/__init__.py
django_comments_ink/conf/defaults.py
django_comments_ink/locale/de/LC_MESSAGES/django.po
django_comments_ink/locale/de/LC_MESSAGES/djangojs.po
django_comments_ink/locale/es/LC_MESSAGES/django.po
django_comments_ink/locale/es/LC_MESSAGES/djangojs.po
django_comments_ink/locale/fi/LC_MESSAGES/django.po
django_comments_ink/locale/fi/LC_MESSAGES/djangojs.po
django_comments_ink/locale/fr/LC_MESSAGES/django.po
django_comments_ink/locale/fr/LC_MESSAGES/djangojs.po
django_comments_ink/locale/it/LC_MESSAGES/django.po
django_comments_ink/locale/it/LC_MESSAGES/djangojs.po
django_comments_ink/locale/nl/LC_MESSAGES/django.po
django_comments_ink/locale/nl/LC_MESSAGES/djangojs.po
django_comments_ink/locale/no/LC_MESSAGES/django.po
django_comments_ink/locale/no/LC_MESSAGES/djangojs.po
django_comments_ink/locale/ru/LC_MESSAGES/django.po
django_comments_ink/locale/ru/LC_MESSAGES/djangojs.po
django_comments_ink/locale/zh_Hans/LC_MESSAGES/django.po
django_comments_ink/locale/zh_Hans/LC_MESSAGES/djangojs.po
django_comments_ink/management/__init__.py
django_comments_ink/management/commands/__init__.py
django_comments_ink/management/commands/populate_comments.py
django_comments_ink/management/commands/update_nested_count.py
django_comments_ink/migrations/0001_initial.py
django_comments_ink/migrations/__init__.py
django_comments_ink/static/django_comments_ink/css/comments.css
django_comments_ink-0.4.0.dist-info/AUTHORS
django_comments_ink-0.4.0.dist-info/LICENSE
django_comments_ink-0.4.0.dist-info/METADATA
django_comments_ink-0.4.0.dist-info/WHEEL
django_comments_ink-0.4.0.dist-info/top_level.txt
django_comments_ink-0.4.0.dist-info/zip-safe
django_comments_ink-0.4.0.dist-info/RECORD
