Metadata-Version: 2.1
Name: django-comments-ink
Version: 0.4.0
Summary: Django pluggable commenting app with comment threads, follow-up notifications, mail confirmation, comment reactions and votes, and comment moderation. It supersedes django-comments-xtd.
Home-page: https://github.com/comments-ink/django-comments-ink
Author: Daniela Rus Morales
Author-email: danirus@eml.cc
Maintainer: Daniela Rus Morales
Maintainer-email: danirus@eml.cc
License: MIT
Classifier: Development Status :: 3 - Alpha
Classifier: Environment :: Web Environment
Classifier: Intended Audience :: Developers
Classifier: License :: OSI Approved :: MIT License
Classifier: Operating System :: OS Independent
Classifier: Programming Language :: Python
Classifier: Programming Language :: Python :: 3
Classifier: Framework :: Django
Classifier: Natural Language :: English
Classifier: Topic :: Internet :: WWW/HTTP :: Dynamic Content :: News/Diary
License-File: LICENSE
License-File: AUTHORS
Requires-Dist: django <6,>=4.1
Requires-Dist: django-contrib-comments <2.3,>=2.2
Requires-Dist: djangorestframework <3.15,>=3.14
